NewsMLG2/__init__.py
NewsMLG2/anyitem.py
NewsMLG2/attributegroups.py
NewsMLG2/catalog.py
NewsMLG2/catalogitem.py
NewsMLG2/catalogstore.py
NewsMLG2/complextypes.py
NewsMLG2/conceptitem.py
NewsMLG2/conceptrelationships.py
NewsMLG2/concepts.py
NewsMLG2/contentmeta.py
NewsMLG2/core.py
NewsMLG2/document.py
NewsMLG2/entities.py
NewsMLG2/events.py
NewsMLG2/extensionproperties.py
NewsMLG2/ids.py
NewsMLG2/itemmanagement.py
NewsMLG2/knowledgeitem.py
NewsMLG2/labeltypes.py
NewsMLG2/link.py
NewsMLG2/newsitem.py
NewsMLG2/newsmessage.py
NewsMLG2/packageitem.py
NewsMLG2/partmeta.py
NewsMLG2/planningitem.py
NewsMLG2/rights.py
NewsMLG2/simpletypes.py
NewsMLG2/utils.py
NewsMLG2/catalogs/__init__.py
NewsMLG2/catalogs/catalog.IPTC-G2-Standards_32.xml
NewsMLG2/catalogs/catalog.IPTC-G2-Standards_33.xml
NewsMLG2/catalogs/catalog.IPTC-G2-Standards_34.xml
NewsMLG2/catalogs/catalog.IPTC-G2-Standards_35.xml
NewsMLG2/catalogs/catalog.IPTC-G2-Standards_36.xml
NewsMLG2/catalogs/catalog.IPTC-G2-Standards_37.xml
NewsMLG2/catalogs/catalog.IPTC-G2-Standards_38.xml
NewsMLG2/catalogs/catalog.IPTC-G2-Standards_39.xml
NewsMLG2/catalogs/catalog.IPTC-G2-Standards_40.xml
newsmlg2-1.0.dist-info/licenses/LICENSE
tests/__init__.py
tests/test_autoloader.py
tests/test_catalogitems.py
tests/test_conceptitems.py
tests/test_core.py
tests/test_events.py
tests/test_knowledgeitems.py
tests/test_newsitems.py
tests/test_newsmessage.py
tests/test_packageitems.py
tests/test_planningitems.py
newsmlg2-1.0.dist-info/METADATA
newsmlg2-1.0.dist-info/WHEEL
newsmlg2-1.0.dist-info/top_level.txt
newsmlg2-1.0.dist-info/RECORD
