Metadata-Version: 2.4
Name: newsmlg2
Version: 1.0
Summary: Python implementation of the NewsML-G2 standard (https://iptc.org/standards/newsml-g2/)
Author-email: Brendan Quinn <office@iptc.org>
License-Expression: MIT
Project-URL: Homepage, https://github.com/iptc/python-newsmlg2/
Keywords: api,media,publishing,news,feed,syndication
Classifier: Development Status :: 5 - Production/Stable
Classifier: Intended Audience :: Developers
Classifier: Programming Language :: Python
Classifier: Programming Language :: Python :: 3
Requires-Python: >=3
License-File: LICENSE
Requires-Dist: lxml
Dynamic: license-file
